{
  "width": 512,
  "height": 512,
    "modified": "Mon Aug 01 2022 23:33:01 GMT+0800 (中国标准时间)",
  "background": "rgb(32,37,46)",
  "dataBindings": [
    {
      "attr": "icon-background",
      "valueType": "Color"
    },
    {
      "attr": "icon-borderWidth",
      "valueType": "PositiveNumber"
    },
    {
      "attr": "icon-borderColor",
      "valueType": "Color"
    }
  ],
"comps": [
    {
      "type": "shape",
      "points": [
        336,
        368.667,
        336,
        208,
        336,
        192.505,
        328.62,
        178.701,
        317.189,
        169.919,
        338.442,
        152.296,
        352,
        125.701,
        352,
        96,
        352,
        43.065,
        308.935,
        0,
        256,
        0,
        203.065,
        0,
        160,
        43.065,
        160,
        96,
        160,
        120.564,
        169.274,
        143.004,
        184.504,
        160,
        184,
        160,
        157.533,
        160,
        136,
        181.533,
        136,
        208,
        136,
        256,
        136,
        279.742,
        153.327,
        299.514,
        176,
        303.333,
        176,
        368.666,
        153.327,
        372.486,
        136,
        392.258,
        136,
        416,
        136,
        464,
        136,
        490.467,
        157.533,
        512,
        184,
        512,
        328,
        512,
        354.467,
        512,
        376,
        490.467,
        376,
        464,
        376,
        416,
        376,
        392.258,
        358.673,
        372.486,
        336,
        368.667,
        256,
        32,
        291.346,
        32,
        320,
        60.654,
        320,
        96,
        320,
        131.346,
        291.346,
        160,
        256,
        160,
        220.654,
        160,
        192,
        131.346,
        192,
        96,
        192,
        60.654,
        220.654,
        32,
        256,
        32,
        344,
        464,
        344,
        472.837,
        336.837,
        480,
        328,
        480,
        184,
        480,
        175.163,
        480,
        168,
        472.837,
        168,
        464,
        168,
        416,
        168,
        407.163,
        175.163,
        400,
        184,
        400,
        208,
        400,
        208,
        272,
        184,
        272,
        175.163,
        272,
        168,
        264.837,
        168,
        256,
        168,
        208,
        168,
        199.163,
        175.163,
        192,
        184,
        192,
        288,
        192,
        296.837,
        192,
        304,
        199.163,
        304,
        208,
        304,
        400,
        328,
        400,
        336.837,
        400,
        344,
        407.163,
        344,
        416,
        344,
        464
      ],
      "segments": [
        1,
        2,
        4,
        4,
        4,
        4,
        4,
        2,
        4,
        2,
        4,
        2,
        4,
        2,
        4,
        2,
        4,
        2,
        4,
        5,
        1,
        4,
        4,
        4,
        4,
        5,
        1,
        4,
        2,
        4,
        2,
        4,
        2,
        2,
        2,
        4,
        2,
        4,
        2,
        4,
        2,
        2,
        4,
        2,
        5
      ],
      "borderColor": null,
      "borderWidth": 0,
      "background": {
  "func": "attr@icon-background",
  "value": "#000000"
}
    }
  ]
}