{
  "width": 512,
  "height": 512,
    "modified": "Mon Aug 01 2022 23:33:01 GMT+0800 (中国标准时间)",
  "background": "rgb(32,37,46)",
  "dataBindings": [
    {
      "attr": "icon-background",
      "valueType": "Color"
    },
    {
      "attr": "icon-borderWidth",
      "valueType": "PositiveNumber"
    },
    {
      "attr": "icon-borderColor",
      "valueType": "Color"
    }
  ],
"comps": [
    {
      "type": "shape",
      "points": [
        497.77778,
        170.66667,
        496,
        170.66667,
        494.22222,
        171.02222,
        492.44444,
        171.73333,
        341.33333,
        227.55556,
        332.17778,
        224.35556,
        352.88889,
        193.33333,
        369.77778,
        161.06667,
        369.77778,
        137.77778,
        369.77778,
        77.33333,
        318.84444,
        28.44444,
        256,
        28.44444,
        193.15556,
        28.44444,
        142.22222,
        77.42222,
        142.22222,
        137.77778,
        142.22222,
        148.26667,
        145.77778,
        160.71111,
        151.46667,
        173.86667,
        17.86667,
        220.44444,
        7.11111,
        224.71111,
        0,
        235.2,
        0,
        246.84444,
        0,
        469.33333,
        0,
        477.51111,
        6.66667,
        483.55556,
        14.22222,
        483.55556,
        16,
        483.55556,
        17.77778,
        483.2,
        19.55556,
        482.48889,
        170.66667,
        426.66667,
        323.55556,
        480.62222,
        335.11111,
        484.44444,
        347.55556,
        484.53333,
        359.11111,
        480.8,
        494.13333,
        433.77778,
        504.97778,
        429.42222,
        512,
        419.02222,
        512,
        407.37778,
        512,
        184.88889,
        512,
        176.71111,
        505.33333,
        170.66667,
        497.77778,
        170.66667,
        156.44444,
        401.6,
        28.35556,
        448.88889,
        27.2,
        247.2,
        156.44444,
        202.31111,
        256,
        56.88889,
        303.02222,
        56.88889,
        341.33333,
        93.15556,
        341.33333,
        137.77778,
        341.33333,
        161.77778,
        307.46667,
        216.8,
        256,
        277.15556,
        204.53333,
        216.8,
        170.66667,
        161.77778,
        170.66667,
        137.77778,
        170.66667,
        93.15556,
        208.97778,
        56.88889,
        256,
        56.88889,
        327.11111,
        451.73333,
        184.88889,
        401.51111,
        184.88889,
        231.82222,
        206.57778,
        263.2,
        231.2,
        292.26667,
        245.06667,
        308,
        247.91111,
        311.28889,
        252,
        312.88889,
        256,
        312.88889,
        260,
        312.88889,
        264,
        311.28889,
        266.93333,
        308,
        278.31111,
        295.11111,
        296.88889,
        273.24444,
        315.2,
        248.53333,
        327.11111,
        252.71111,
        355.55556,
        451.91111,
        355.55556,
        252.62222,
        483.64444,
        205.33333,
        484.8,
        407.02222,
        277.33333,
        142.22222,
        277.33333,
        130.4,
        267.73333,
        120.88889,
        256,
        120.88889,
        244.26667,
        120.88889,
        234.66667,
        130.4,
        234.66667,
        142.22222,
        234.66667,
        153.95556,
        244.26667,
        163.55556,
        256,
        163.55556,
        267.73333,
        163.55556,
        277.33333,
        154.04444,
        277.33333,
        142.22222
      ],
      "segments": [
        1,
        4,
        2,
        2,
        4,
        4,
        4,
        4,
        2,
        4,
        2,
        4,
        4,
        2,
        2,
        4,
        2,
        4,
        2,
        4,
        5,
        1,
        2,
        2,
        2,
        5,
        1,
        4,
        4,
        4,
        4,
        5,
        1,
        2,
        2,
        4,
        4,
        4,
        4,
        2,
        5,
        1,
        2,
        2,
        2,
        5,
        1,
        4,
        4,
        4,
        4,
        5
      ],
      "borderColor": null,
      "borderWidth": 0,
      "background": {
  "func": "attr@icon-background",
  "value": "#000000"
}
    }
  ]
}