{
  "width": 512,
  "height": 512,
    "modified": "Mon Aug 01 2022 23:33:01 GMT+0800 (中国标准时间)",
  "background": "rgb(32,37,46)",
  "dataBindings": [
    {
      "attr": "icon-background",
      "valueType": "Color"
    },
    {
      "attr": "icon-borderWidth",
      "valueType": "PositiveNumber"
    },
    {
      "attr": "icon-borderColor",
      "valueType": "Color"
    }
  ],
"comps": [
    {
      "type": "shape",
      "points": [
        486.4,
        51.2,
        271.072,
        51.2,
        153.6,
        51.2,
        51.2,
        102.4,
        0,
        230.4,
        448.144,
        230.4,
        437.696,
        281.6,
        313.6,
        281.6,
        310.08906,
        281.6,
        307.2,
        284.48906,
        307.2,
        288,
        307.2,
        300.8,
        307.2,
        304.31094,
        310.08906,
        307.2,
        313.6,
        307.2,
        432.48,
        307.2,
        403.248,
        450.48,
        402.9004,
        452.14181,
        403.22795,
        453.8755,
        404.15791,
        455.29594,
        405.08787,
        456.71637,
        406.54586,
        457.70996,
        408.208,
        458.056,
        420.728,
        460.664,
        421.15919,
        460.75628,
        421.59905,
        460.80188,
        422.04,
        460.8,
        425.05714,
        460.7954,
        427.68126,
        458.65785,
        428.296,
        455.704,
        511.376,
        82.4,
        513.07516,
        74.82055,
        511.23551,
        66.86549,
        506.38125,
        60.80156,
        501.52699,
        54.73762,
        494.16757,
        51.20121,
        486.4,
        51.2,
        457.904,
        204.8,
        40.32,
        204.8,
        98.096,
        100.048,
        195.784,
        76.8,
        271.072,
        76.8,
        486.4,
        76.8
      ],
      "segments": [
        1,
        2,
        4,
        2,
        2,
        2,
        4,
        2,
        4,
        2,
        2,
        4,
        4,
        2,
        4,
        4,
        2,
        4,
        4,
        5,
        1,
        2,
        4,
        2,
        5
      ],
      "borderColor": null,
      "borderWidth": 0,
      "background": {
  "func": "attr@icon-background",
  "value": "#000000"
}
    }
  ]
}