{
  "width": 512,
  "height": 512,
    "modified": "Mon Aug 01 2022 23:33:01 GMT+0800 (中国标准时间)",
  "background": "rgb(32,37,46)",
  "dataBindings": [
    {
      "attr": "icon-background",
      "valueType": "Color"
    },
    {
      "attr": "icon-borderWidth",
      "valueType": "PositiveNumber"
    },
    {
      "attr": "icon-borderColor",
      "valueType": "Color"
    }
  ],
"comps": [
    {
      "type": "shape",
      "points": [
        504,
        160,
        272,
        160,
        272,
        96,
        440,
        96,
        444.42,
        96,
        448,
        92.42,
        448,
        88,
        448,
        72,
        448,
        67.58,
        444.42,
        64,
        440,
        64,
        272,
        64,
        272,
        8,
        272,
        3.58,
        268.42,
        0,
        264,
        0,
        248,
        0,
        243.58,
        0,
        240,
        3.58,
        240,
        8,
        240,
        64,
        72,
        64,
        67.58,
        64,
        64,
        67.58,
        64,
        72,
        64,
        88,
        64,
        92.42,
        67.58,
        96,
        72,
        96,
        240,
        96,
        240,
        160,
        8,
        160,
        3.58,
        160,
        0,
        163.58,
        0,
        168,
        0,
        184,
        0,
        188.42,
        3.58,
        192,
        8,
        192,
        240,
        192,
        240,
        256,
        72,
        256,
        67.58,
        256,
        64,
        259.58,
        64,
        264,
        64,
        280,
        64,
        284.42,
        67.58,
        288,
        72,
        288,
        240,
        288,
        240,
        352,
        112,
        352,
        67.82,
        352,
        32,
        387.82,
        32,
        432,
        32,
        476.18,
        67.82,
        512,
        112,
        512,
        156.18,
        512,
        192,
        476.18,
        192,
        432,
        192,
        413.9,
        185.77,
        397.4,
        175.64,
        384,
        336.36,
        384,
        326.23,
        397.4,
        320,
        413.9,
        320,
        432,
        320,
        476.18,
        355.82,
        512,
        400,
        512,
        444.18,
        512,
        480,
        476.18,
        480,
        432,
        480,
        387.82,
        444.18,
        352,
        400,
        352,
        272,
        352,
        272,
        288,
        440,
        288,
        444.42,
        288,
        448,
        284.42,
        448,
        280,
        448,
        264,
        448,
        259.58,
        444.42,
        256,
        440,
        256,
        272,
        256,
        272,
        192,
        504,
        192,
        508.42,
        192,
        512,
        188.42,
        512,
        184,
        512,
        168,
        512,
        163.58,
        508.42,
        160,
        504,
        160,
        160,
        432,
        160,
        458.47,
        138.47,
        480,
        112,
        480,
        85.53,
        480,
        64,
        458.47,
        64,
        432,
        64,
        405.53,
        85.53,
        384,
        112,
        384,
        138.47,
        384,
        160,
        405.53,
        160,
        432,
        448,
        432,
        448,
        458.47,
        426.47,
        480,
        400,
        480,
        373.53,
        480,
        352,
        458.47,
        352,
        432,
        352,
        405.53,
        373.53,
        384,
        400,
        384,
        426.47,
        384,
        448,
        405.53,
        448,
        432
      ],
      "segments": [
        1,
        2,
        2,
        2,
        4,
        2,
        4,
        2,
        2,
        4,
        2,
        4,
        2,
        2,
        4,
        2,
        4,
        2,
        2,
        2,
        4,
        2,
        4,
        2,
        2,
        2,
        4,
        2,
        4,
        2,
        2,
        2,
        4,
        4,
        4,
        4,
        2,
        4,
        4,
        4,
        4,
        2,
        2,
        2,
        4,
        2,
        4,
        2,
        2,
        2,
        4,
        2,
        4,
        5,
        1,
        4,
        4,
        4,
        4,
        5,
        1,
        4,
        4,
        4,
        4,
        5
      ],
      "borderColor": null,
      "borderWidth": 0,
      "background": {
  "func": "attr@icon-background",
  "value": "#000000"
}
    }
  ]
}