{
  "modified": "Sat May 11 2024 11:08:20 GMT+0800 (中国标准时间)",
  "dataBindings": [
    {
      "attr": "icon-background",
      "valueType": "Color"
    },
    {
      "attr": "icon-borderWidth",
      "valueType": "PositiveNumber"
    },
    {
      "attr": "icon-borderColor",
      "valueType": "Color"
    }
  ],
  "width": 45,
  "height": 45,
  "comps": [
    {
      "type": "shape",
      "background": {
        "func": "attr@icon-background",
        "value": "rgba(55,125,255)"
      },
      "borderWidth": {
        "func": "attr@icon-borderWidth",
        "value": 0
      },
      "borderColor": {
        "func": "attr@icon-borderColor",
        "value": null
      },
      "anchorX": 0,
      "anchorY": 0,
      "scaleX": 4.5,
      "scaleY": 4.5,
      "points": [
        12.1201,
        19.83738,
        12.00123,
        19.83738,
        11.90362,
        19.93498,
        11.90362,
        20.05386,
        11.90362,
        23.75147,
        4.64104,
        23.75147,
        4.64104,
        20.05386,
        4.64104,
        19.93498,
        4.54342,
        19.83738,
        4.42455,
        19.83738,
        4.30568,
        19.83738,
        4.20809,
        19.93498,
        4.20809,
        20.05386,
        4.20809,
        24.18443,
        12.33783,
        24.18443,
        12.33783,
        20.05386,
        12.33658,
        19.93374,
        12.23897,
        19.83738,
        12.1201,
        19.83738
      ],
      "segments": [
        1,
        4,
        2,
        2,
        2,
        4,
        4,
        2,
        2,
        2,
        4,
        5
      ]
    },
    {
      "type": "shape",
      "background": {
        "func": "attr@icon-background",
        "value": "rgba(55,125,255)"
      },
      "borderWidth": {
        "func": "attr@icon-borderWidth",
        "value": 0
      },
      "borderColor": {
        "func": "attr@icon-borderColor",
        "value": null
      },
      "anchorX": 0,
      "anchorY": 0,
      "scaleX": 4.5,
      "scaleY": 4.5,
      "points": [
        21.52586,
        11.86091,
        21.52586,
        17.59565,
        21.52586,
        17.71453,
        21.62346,
        17.81213,
        21.74233,
        17.81213,
        21.86121,
        17.81213,
        21.95881,
        17.71453,
        21.95881,
        17.59565,
        21.95881,
        11.86091,
        21.95881,
        11.74079,
        21.86121,
        11.64443,
        21.74233,
        11.64443,
        21.62346,
        11.64443,
        21.52586,
        11.74203,
        21.52586,
        11.86091
      ],
      "segments": [
        1,
        2,
        4,
        4,
        2,
        4,
        4,
        5
      ]
    },
    {
      "type": "shape",
      "background": {
        "func": "attr@icon-background",
        "value": "rgba(55,125,255)"
      },
      "borderWidth": {
        "func": "attr@icon-borderWidth",
        "value": 0
      },
      "borderColor": {
        "func": "attr@icon-borderColor",
        "value": null
      },
      "anchorX": 0,
      "anchorY": 0,
      "scaleX": 4.5,
      "scaleY": 4.5,
      "points": [
        9.26178,
        10.82263,
        11.87075,
        8.13107,
        14.53604,
        10.82513,
        14.61988,
        10.90897,
        14.75752,
        10.91022,
        14.84136,
        10.82764,
        14.9252,
        10.7438,
        14.92645,
        10.60616,
        14.84387,
        10.52232,
        12.02342,
        7.66933,
        12.02091,
        7.66683,
        12.01841,
        7.66433,
        12.01591,
        7.66182,
        12.0134,
        7.66058,
        12.0109,
        7.65683,
        12.0034,
        7.64932,
        12.0009,
        7.64682,
        11.99714,
        7.64431,
        11.99463,
        7.64181,
        11.99213,
        7.63931,
        11.98838,
        7.63805,
        11.98588,
        7.63556,
        11.98338,
        7.63304,
        11.97837,
        7.6318,
        11.97712,
        7.62929,
        11.97462,
        7.62679,
        11.97086,
        7.62554,
        11.96836,
        7.62429,
        11.96461,
        7.62178,
        11.96085,
        7.62178,
        11.95834,
        7.61928,
        11.95584,
        7.61804,
        11.95209,
        7.61678,
        11.94959,
        7.61553,
        11.94584,
        7.61303,
        11.94208,
        7.61303,
        11.93833,
        7.61177,
        11.93583,
        7.61053,
        11.93208,
        7.60928,
        11.93082,
        7.60928,
        11.92707,
        7.60802,
        11.92206,
        7.60678,
        11.9183,
        7.60678,
        11.9158,
        7.60552,
        11.9133,
        7.60552,
        11.91079,
        7.60427,
        11.9058,
        7.60302,
        11.90204,
        7.60177,
        11.89703,
        7.60177,
        11.89453,
        7.60177,
        11.89328,
        7.60051,
        11.89078,
        7.60051,
        11.88327,
        7.59927,
        11.87702,
        7.59927,
        11.87075,
        7.59927,
        11.86326,
        7.59927,
        11.85699,
        7.59927,
        11.84948,
        7.60051,
        11.84698,
        7.60051,
        11.84573,
        7.60177,
        11.84323,
        7.60177,
        11.83822,
        7.60302,
        11.83446,
        7.60302,
        11.82947,
        7.60427,
        11.82696,
        7.60552,
        11.82446,
        7.60552,
        11.82196,
        7.60678,
        11.8182,
        7.60802,
        11.81319,
        7.60928,
        11.80944,
        7.60928,
        11.80694,
        7.61053,
        11.80319,
        7.61177,
        11.80069,
        7.61177,
        11.78942,
        7.61553,
        11.78691,
        7.61678,
        11.78317,
        7.61804,
        11.78066,
        7.61928,
        11.77691,
        7.62178,
        11.77315,
        7.62178,
        11.77065,
        7.62429,
        11.76815,
        7.62679,
        11.7644,
        7.62805,
        11.76189,
        7.62929,
        11.75939,
        7.6318,
        11.75438,
        7.63304,
        11.75314,
        7.63556,
        11.75063,
        7.63805,
        11.74687,
        7.63931,
        11.74437,
        7.64181,
        11.74187,
        7.64431,
        11.73812,
        7.64682,
        11.73562,
        7.64932,
        11.73311,
        7.65182,
        11.72936,
        7.65433,
        11.72811,
        7.65683,
        11.7256,
        7.65932,
        11.7231,
        7.66058,
        11.7206,
        7.66308,
        11.71809,
        7.66558,
        11.71559,
        7.66809,
        8.95021,
        10.52232,
        8.86761,
        10.6074,
        8.86887,
        10.7463,
        8.9552,
        10.82764,
        9.04155,
        10.91022,
        9.17794,
        10.90772,
        9.26178,
        10.82263
      ],
      "segments": [
        1,
        2,
        2,
        4,
        4,
        2,
        2,
        2,
        4,
        2,
        4,
        4,
        4,
        4,
        4,
        4,
        4,
        4,
        4,
        4,
        4,
        4,
        4,
        4,
        4,
        4,
        4,
        4,
        4,
        2,
        4,
        4,
        4,
        4,
        4,
        4,
        4,
        4,
        2,
        2,
        2,
        4,
        4,
        5
      ]
    }
  ]
}