{
  "modified": "Sat May 11 2024 11:09:25 GMT+0800 (中国标准时间)",
  "dataBindings": [
    {
      "attr": "icon-background",
      "valueType": "Color"
    },
    {
      "attr": "icon-borderWidth",
      "valueType": "PositiveNumber"
    },
    {
      "attr": "icon-borderColor",
      "valueType": "Color"
    }
  ],
  "width": 45,
  "height": 45,
  "comps": [
    {
      "type": "shape",
      "background": {
        "func": "attr@icon-background",
        "value": "rgba(55,125,255)"
      },
      "borderWidth": {
        "func": "attr@icon-borderWidth",
        "value": 0
      },
      "borderColor": {
        "func": "attr@icon-borderColor",
        "value": null
      },
      "anchorX": 0,
      "anchorY": 0,
      "scaleX": 4.5,
      "scaleY": 4.5,
      "points": [
        8.90625,
        4.71289,
        8.78516,
        4.71289,
        8.68652,
        4.81152,
        8.68652,
        4.93262,
        8.68652,
        8.68652,
        1.31348,
        8.68652,
        1.31348,
        4.93262,
        1.31348,
        4.81152,
        1.21484,
        4.71289,
        1.09375,
        4.71289,
        0.97266,
        4.71289,
        0.87402,
        4.81152,
        0.87402,
        4.93262,
        0.87402,
        9.12598,
        9.12598,
        9.12598,
        9.12598,
        4.93262,
        9.12598,
        4.81152,
        9.02734,
        4.71289,
        8.90625,
        4.71289,
        5,
        7.13574,
        5.12109,
        7.13574,
        5.21973,
        7.03711,
        5.21973,
        6.91602,
        5.21973,
        1.09375,
        5.21973,
        0.97266,
        5.12109,
        0.87402,
        5,
        0.87402,
        4.87891,
        0.87402,
        4.78027,
        0.97266,
        4.78027,
        1.09375,
        4.78027,
        6.91602,
        4.78027,
        7.03711,
        4.87891,
        7.13574,
        5,
        7.13574,
        4.84375,
        8.12695,
        4.8457,
        8.12891,
        4.84766,
        8.13086,
        4.84961,
        8.13281,
        4.85254,
        8.13477,
        4.85449,
        8.1377,
        4.85742,
        8.13965,
        4.85938,
        8.14258,
        4.8623,
        8.14453,
        4.86523,
        8.14746,
        4.86816,
        8.14941,
        4.87207,
        8.15137,
        4.88086,
        8.15723,
        4.88379,
        8.15918,
        4.8877,
        8.16113,
        4.89063,
        8.16309,
        4.89355,
        8.16504,
        4.89648,
        8.16699,
        4.89941,
        8.16797,
        4.90332,
        8.16992,
        4.90625,
        8.1709,
        4.91016,
        8.17285,
        4.91309,
        8.17383,
        4.91602,
        8.17578,
        4.91895,
        8.17676,
        4.92285,
        8.17871,
        4.92676,
        8.17969,
        4.93066,
        8.18066,
        4.93359,
        8.18164,
        4.93652,
        8.18262,
        4.93848,
        8.18359,
        4.94238,
        8.18457,
        4.94727,
        8.18555,
        4.95117,
        8.18652,
        4.9541,
        8.1875,
        4.95605,
        8.1875,
        4.95898,
        8.18848,
        4.96387,
        8.18945,
        4.96875,
        8.19043,
        4.97363,
        8.19043,
        4.97559,
        8.19043,
        4.97754,
        8.19141,
        4.97949,
        8.19141,
        4.98633,
        8.19238,
        4.99316,
        8.19238,
        5,
        8.19238,
        5.00684,
        8.19238,
        5.01465,
        8.19238,
        5.02148,
        8.19141,
        5.02344,
        8.19141,
        5.02539,
        8.19043,
        5.02734,
        8.19043,
        5.03223,
        8.18945,
        5.03711,
        8.18945,
        5.04199,
        8.18848,
        5.04492,
        8.1875,
        5.04688,
        8.1875,
        5.0498,
        8.18652,
        5.05371,
        8.18555,
        5.05859,
        8.18457,
        5.0625,
        8.18359,
        5.07129,
        8.18066,
        5.0752,
        8.17969,
        5.0791,
        8.17773,
        5.08301,
        8.17676,
        5.08594,
        8.17578,
        5.08887,
        8.17383,
        5.0918,
        8.17285,
        5.0957,
        8.1709,
        5.09863,
        8.16992,
        5.10254,
        8.16797,
        5.10547,
        8.16602,
        5.1084,
        8.16406,
        5.11133,
        8.16309,
        5.11426,
        8.16113,
        5.11816,
        8.15918,
        5.12109,
        8.15723,
        5.12988,
        8.15137,
        5.13281,
        8.14941,
        5.13574,
        8.14648,
        5.13867,
        8.14453,
        5.1416,
        8.14258,
        5.14453,
        8.13965,
        5.14648,
        8.1377,
        5.14844,
        8.13574,
        5.15137,
        8.13379,
        5.15332,
        8.13184,
        5.15527,
        8.12988,
        5.15723,
        8.12793,
        7.96094,
        5.23438,
        8.04492,
        5.14746,
        8.04297,
        5.00781,
        7.95605,
        4.92383,
        7.86914,
        4.83984,
        7.72949,
        4.8418,
        7.64551,
        4.92871,
        4.99902,
        7.6582,
        2.29297,
        4.92383,
        2.20801,
        4.83789,
        2.06836,
        4.83691,
        1.98242,
        4.92188,
        1.89648,
        5.00684,
        1.89551,
        5.14648,
        1.98047,
        5.23242,
        4.84375,
        8.12695
      ],
      "segments": [
        1,
        4,
        2,
        2,
        2,
        4,
        4,
        2,
        2,
        2,
        4,
        5,
        1,
        4,
        2,
        4,
        4,
        2,
        4,
        5,
        1,
        2,
        2,
        4,
        4,
        4,
        2,
        4,
        4,
        4,
        4,
        4,
        4,
        4,
        4,
        4,
        4,
        4,
        4,
        4,
        4,
        4,
        4,
        2,
        4,
        4,
        4,
        4,
        4,
        2,
        4,
        4,
        4,
        2,
        2,
        2,
        4,
        4,
        2,
        2,
        4,
        4,
        2,
        5
      ]
    }
  ]
}