{
  "modified": "Sat May 11 2024 10:47:47 GMT+0800 (中国标准时间)",
  "dataBindings": [
    {
      "attr": "icon-background",
      "valueType": "Color"
    },
    {
      "attr": "icon-borderWidth",
      "valueType": "PositiveNumber"
    },
    {
      "attr": "icon-borderColor",
      "valueType": "Color"
    }
  ],
  "width": 45,
  "height": 45,
  "comps": [
    {
      "type": "shape",
      "background": {
        "func": "attr@icon-background",
        "value": "rgba(55,125,255)"
      },
      "borderWidth": {
        "func": "attr@icon-borderWidth",
        "value": 0
      },
      "borderColor": {
        "func": "attr@icon-borderColor",
        "value": null
      },
      "anchorX": 0,
      "anchorY": 0,
      "scaleX": 4.5,
      "scaleY": 4.5,
      "points": [
        8,
        8.14083,
        8.11894,
        8.14083,
        8.2292,
        8.20449,
        8.28868,
        8.3075,
        8.34815,
        8.41051,
        8.34815,
        8.53783,
        8.28868,
        8.64083,
        8.2292,
        8.74384,
        8.11894,
        8.8075,
        8,
        8.8075,
        2,
        8.8075,
        1.88106,
        8.8075,
        1.7708,
        8.74384,
        1.71132,
        8.64083,
        1.65185,
        8.53783,
        1.65185,
        8.41051,
        1.71132,
        8.3075,
        1.7708,
        8.20449,
        1.88106,
        8.14083,
        2,
        8.14083,
        8,
        8.14083,
        5,
        1.33333,
        6.23042,
        1.33333,
        7.22708,
        2.33542,
        7.22708,
        3.57083,
        7.22708,
        4.17167,
        6.99,
        4.73542,
        6.57542,
        5.15208,
        6.53398,
        5.19317,
        6.48986,
        5.23145,
        6.44333,
        5.26667,
        6.40542,
        5.29583,
        6.36417,
        5.32542,
        6.31875,
        5.35583,
        6.20625,
        5.42792,
        6.12042,
        5.48042,
        6.04917,
        5.52208,
        6.05792,
        5.88167,
        6.05792,
        5.9025,
        7.65167,
        5.9025,
        8.00042,
        5.9025,
        8.32542,
        6.05667,
        8.36042,
        6.36917,
        8.36375,
        6.42625,
        8.36375,
        7.18792,
        8.36375,
        7.52,
        8.05792,
        7.69208,
        7.71292,
        7.71,
        7.65167,
        7.71125,
        2.34833,
        7.71125,
        1.99958,
        7.71125,
        1.67458,
        7.55792,
        1.63958,
        7.24458,
        1.63625,
        7.18792,
        1.63625,
        6.42625,
        1.63625,
        6.09458,
        1.94208,
        5.92208,
        2.28708,
        5.90417,
        2.34833,
        5.90292,
        3.9425,
        5.90208,
        3.9425,
        5.85125,
        3.95292,
        5.525,
        3.79375,
        5.42917,
        3.75,
        5.40208,
        3.68351,
        5.35989,
        3.61886,
        5.31485,
        3.55625,
        5.26708,
        3.50992,
        5.23179,
        3.46593,
        5.19352,
        3.42458,
        5.1525,
        3.00648,
        4.73264,
        2.77193,
        4.16336,
        2.77292,
        3.57083,
        2.77292,
        2.33542,
        3.76958,
        1.33333,
        5,
        1.33333,
        5,
        2,
        4.13833,
        2,
        3.43958,
        2.70292,
        3.43958,
        3.57083,
        3.43958,
        3.99375,
        3.60583,
        4.38917,
        3.89708,
        4.68208,
        3.915,
        4.69875,
        3.96333,
        4.73875,
        3.99,
        4.75958,
        4.02083,
        4.78167,
        4.05542,
        4.80458,
        4.13167,
        4.85375,
        4.36542,
        4.99583,
        4.435,
        5.03917,
        4.49542,
        5.07917,
        4.51292,
        5.09708,
        4.57078,
        5.14859,
        4.60637,
        5.22066,
        4.61208,
        5.29792,
        4.61875,
        5.37542,
        4.62042,
        5.48083,
        4.60833,
        5.93375,
        4.60833,
        6.23542,
        4.60839,
        6.40265,
        4.48259,
        6.54535,
        4.31667,
        6.56625,
        4.275,
        6.56917,
        2.32917,
        6.57,
        2.30292,
        6.57208,
        2.30292,
        7.04167,
        2.31125,
        7.04333,
        2.34875,
        7.04458,
        7.67083,
        7.04458,
        7.69667,
        7.04167,
        7.69667,
        6.57208,
        7.68917,
        6.57125,
        7.65167,
        6.56958,
        5.725,
        6.56958,
        5.54214,
        6.56958,
        5.39167,
        6.41911,
        5.39167,
        6.23625,
        5.39167,
        6.23583,
        5.39083,
        5.86125,
        5.38208,
        5.45458,
        5.38333,
        5.37958,
        5.385,
        5.34792,
        5.39167,
        5.24792,
        5.39917,
        5.20792,
        5.46,
        5.12833,
        5.48214,
        5.10437,
        5.50703,
        5.08311,
        5.53417,
        5.065,
        5.61333,
        5.01,
        5.70167,
        4.95333,
        5.89042,
        4.83917,
        5.94833,
        4.8025,
        5.9975,
        4.76833,
        6.0375,
        4.73792,
        6.08542,
        4.69833,
        6.38961,
        4.40234,
        6.56111,
        3.99527,
        6.56042,
        3.57083,
        6.56042,
        2.70292,
        5.86167,
        2,
        5,
        2
      ],
      "segments": [
        1,
        4,
        4,
        4,
        2,
        4,
        4,
        4,
        2,
        5,
        1,
        4,
        4,
        4,
        4,
        2,
        2,
        2,
        2,
        2,
        2,
        4,
        2,
        2,
        4,
        2,
        2,
        4,
        2,
        2,
        4,
        2,
        2,
        2,
        2,
        2,
        2,
        4,
        4,
        4,
        4,
        5,
        1,
        4,
        4,
        2,
        2,
        4,
        2,
        2,
        4,
        4,
        2,
        2,
        2,
        2,
        4,
        2,
        2,
        2,
        2,
        2,
        2,
        2,
        2,
        2,
        2,
        2,
        2,
        4,
        2,
        2,
        2,
        2,
        2,
        4,
        4,
        2,
        2,
        2,
        4,
        2,
        4,
        4,
        5
      ]
    }
  ]
}