{
    "width": 512,
    "height": 512,
    "modified": "Mon Aug 01 2022 23:33:01 GMT+0800 (中国标准时间)",
    "background": "rgb(32,37,46)",
    "dataBindings": [{
            "attr": "icon-background",
            "valueType": "Color"
        },
        {
            "attr": "icon-borderWidth",
            "valueType": "PositiveNumber"
        },
        {
            "attr": "icon-borderColor",
            "valueType": "Color"
        }
    ],
    "comps": [{
        "type": "shape",
        "points": [
            304,
            106.688,
            311.96579,
            106.68979,
            318.77794,
            112.64011,
            319.85067,
            120.53333,
            320,
            122.66667,
            320,
            138.70933,
            320,
            152.21333,
            315.81867,
            164.736,
            308.69333,
            175.06133,
            339.03593,
            185.50317,
            360.28484,
            213.23379,
            362.47467,
            245.248,
            367.936,
            245.26933,
            380.66155,
            245.2129,
            392.85645,
            240.09806,
            401.81478,
            231.05975,
            410.77311,
            222.02143,
            415.77935,
            209.78155,
            415.72267,
            197.056,
            415.59467,
            165.376,
            415.55956,
            156.59866,
            422.75333,
            149.34711,
            431.53067,
            149.312,
            440.30801,
            149.27689,
            447.55956,
            156.47066,
            447.59467,
            165.248,
            447.744,
            196.928,
            447.92569,
            239.22308,
            414.5359,
            274.72806,
            372.30933,
            277.14133,
            367.744,
            277.26933,
            362.66667,
            277.26933,
            362.66667,
            309.29067,
            453.39733,
            309.312,
            461.3562,
            309.31234,
            468.16559,
            315.25108,
            469.248,
            323.136,
            469.39733,
            325.312,
            469.397,
            333.27087,
            463.45825,
            340.08026,
            455.57333,
            341.16267,
            453.39733,
            341.312,
            362.66667,
            341.312,
            362.66667,
            383.97867,
            367.744,
            383.97867,
            372.30933,
            384.10667,
            412.93645,
            386.43424,
            445.64214,
            419.40853,
            447.63733,
            460.05333,
            447.744,
            464.32,
            447.59467,
            496,
            447.52735,
            504.34185,
            440.9468,
            511.30261,
            432.62187,
            511.83791,
            424.29694,
            512.3732,
            416.87911,
            506.31253,
            415.744,
            498.048,
            415.59467,
            495.872,
            415.744,
            464.17067,
            415.84338,
            439.07718,
            396.24909,
            417.92437,
            371.22133,
            416.10667,
            367.936,
            415.97867,
            357.78133,
            415.97867,
            343.82565,
            460.29264,
            302.45955,
            490.63426,
            256,
            490.63426,
            209.54045,
            490.63426,
            168.17435,
            460.29264,
            154.21867,
            415.97867,
            143.78667,
            415.97867,
            131.06112,
            416.0351,
            118.86621,
            421.14994,
            109.90789,
            430.18825,
            100.94956,
            439.22657,
            95.94332,
            451.46645,
            96,
            464.192,
            96.10667,
            495.872,
            96.1295,
            501.58115,
            93.09495,
            506.88605,
            88.16209,
            509.76041,
            83.22924,
            512.63476,
            77.11778,
            512.65921,
            72.16209,
            509.82441,
            67.2064,
            506.98961,
            64.1295,
            501.70915,
            64.10667,
            496,
            64,
            464.32,
            63.829,
            422.04048,
            97.203,
            386.5517,
            139.41333,
            384.128,
            144,
            384,
            149.33333,
            384,
            149.33333,
            341.33333,
            58.66667,
            341.33333,
            50.7078,
            341.333,
            43.89841,
            335.39425,
            42.816,
            327.50933,
            42.66667,
            325.33333,
            42.667,
            317.37447,
            48.60575,
            310.56507,
            56.49067,
            309.48267,
            58.66667,
            309.33333,
            149.33333,
            309.33333,
            149.33333,
            277.248,
            144,
            277.26933,
            139.41333,
            277.14133,
            98.79436,
            274.80331,
            66.10087,
            241.83197,
            64.10667,
            201.19467,
            64,
            196.94933,
            64.128,
            165.26933,
            64.10166,
            156.86378,
            70.70335,
            149.7974,
            79.09128,
            149.25281,
            87.47921,
            148.70821,
            94.93922,
            154.86161,
            96,
            163.2,
            96.128,
            165.376,
            96,
            197.12,
            95.90062,
            222.21349,
            115.49491,
            243.3663,
            140.52267,
            245.184,
            143.808,
            245.312,
            149.52533,
            245.312,
            151.70702,
            213.28014,
            172.9541,
            185.52661,
            203.30667,
            175.06133,
            196.7675,
            165.65239,
            192.90336,
            154.64254,
            192.128,
            143.21067,
            192,
            138.73067,
            192,
            122.688,
            192.01363,
            114.32727,
            198.57839,
            107.31488,
            206.92006,
            106.75058,
            215.26174,
            106.18627,
            222.71112,
            112.25062,
            223.85067,
            120.53333,
            224,
            122.688,
            224,
            138.73067,
            223.99711,
            155.70361,
            237.49848,
            169.87732,
            254.45153,
            170.69863,
            271.40459,
            171.51995,
            286.21284,
            158.71773,
            287.85067,
            141.824,
            288,
            138.73067,
            288,
            122.688,
            288,
            113.91066,
            295.22266,
            106.688,
            304,
            106.688
        ],
        "segments": [
            1,
            4,
            2,
            2,
            4,
            4,
            2,
            4,
            4,
            2,
            4,
            4,
            2,
            4,
            2,
            2,
            2,
            2,
            4,
            2,
            4,
            2,
            2,
            2,
            2,
            2,
            4,
            2,
            2,
            4,
            4,
            2,
            2,
            4,
            2,
            2,
            4,
            4,
            2,
            4,
            4,
            2,
            4,
            4,
            4,
            2,
            4,
            2,
            2,
            2,
            2,
            4,
            2,
            4,
            2,
            2,
            2,
            2,
            2,
            4,
            2,
            2,
            4,
            4,
            2,
            2,
            4,
            2,
            2,
            4,
            4,
            2,
            2,
            4,
            4,
            2,
            2,
            4,
            4,
            2,
            2,
            4,
            5
        ],
        "borderColor": {
            "func": "attr@icon-borderColor",
            "value": "#000000"
        },
         "borderWidth": {
     "func": "attr@icon-borderWidth",
     "value": 0
 },
        "background": {
            "func": "attr@icon-background",
            "value": "#000000"
        }
    }]
}