{
    "width": 512,
    "height": 512,
    "modified": "Mon Aug 01 2022 23:33:01 GMT+0800 (中国标准时间)",
    "background": "rgb(32,37,46)",
    "dataBindings": [{
            "attr": "icon-background",
            "valueType": "Color"
        },
        {
            "attr": "icon-borderWidth",
            "valueType": "PositiveNumber"
        },
        {
            "attr": "icon-borderColor",
            "valueType": "Color"
        }
    ],
    "comps": [{
        "type": "shape",
        "points": [
            213.33333,
            117.33333,
            274.07295,
            117.33089,
            329.78613,
            151.91585,
            356.73263,
            206.35101,
            383.67912,
            260.78618,
            377.39784,
            326.05963,
            340.56533,
            374.35733,
            441.74933,
            475.584,
            449.64522,
            483.50674,
            450.0378,
            496.36286,
            442.64002,
            504.75261,
            435.24225,
            513.14236,
            422.4381,
            514.36209,
            413.58933,
            507.52,
            411.584,
            505.74933,
            310.35733,
            404.56533,
            255.02595,
            446.75602,
            178.22418,
            448.2379,
            121.30646,
            408.21305,
            64.38874,
            368.1882,
            39.80568,
            295.41196,
            60.79419,
            229.07119,
            81.78271,
            162.73042,
            143.75161,
            117.33701,
            213.33333,
            117.33333,
            213.33333,
            160,
            171.4644,
            159.99727,
            132.64856,
            182.40535,
            111.7133,
            218.66446,
            90.77804,
            254.92356,
            90.77804,
            299.7431,
            111.7133,
            336.00221,
            132.64856,
            372.26132,
            171.4644,
            394.6694,
            213.33333,
            394.66667,
            277.6976,
            394.66246,
            330.65901,
            341.6976,
            330.65901,
            277.33333,
            330.65901,
            212.96907,
            277.6976,
            160.0042,
            213.33333,
            160
        ],
        "segments": [
            1,
            4,
            4,
            2,
            4,
            4,
            2,
            2,
            4,
            4,
            4,
            5,
            1,
            4,
            4,
            4,
            4,
            4,
            5
        ],
        "borderColor": {
            "func": "attr@icon-borderColor",
            "value": "#000000"
        },
         "borderWidth": {
     "func": "attr@icon-borderWidth",
     "value": 0
 },
        "background": {
            "func": "attr@icon-background",
            "value": "#000000"
        }
    }]
}